_FFPopSim.abi3.so
FFPopSim.py
FFPopSim.libs/libgfortran-91cc3cb1.so.3.0.0
FFPopSim.libs/libgsl-cb3064f9.so.0.16.0
FFPopSim.libs/libquadmath-96973f99.so.0.0.0
FFPopSim.libs/libsatlas-7e2f78d2.so.3.10
FFPopSim.libs/libgslcblas-9055a056.so.0.0.0
FFPopSim-3.1.2.dist-info/WHEEL
FFPopSim-3.1.2.dist-info/RECORD
FFPopSim-3.1.2.dist-info/top_level.txt
FFPopSim-3.1.2.dist-info/METADATA
