Metadata-Version: 2.1
Name: FFPopSim
Version: 3.1.2
Summary: Library to simulate evolution of large populations that are polymorphic at many loci.
Home-page: UNKNOWN
Author: Fabio Zanini,Ivan Aksamentov
Author-email: Richard Neher <richard.neher@unibas.ch>
License: UNKNOWN
Project-URL: homepage, https://github.com/neherlab/ffpopsim
Project-URL: documentation, https://readthedocs.org/projects/ffpopsim
Project-URL: repository, https://github.com/neherlab/ffpopsim
Keywords: packaging,dependency,infer,pyproject.toml
Platform: UNKNOWN
Classifier: Programming Language :: Python :: 3
Classifier: Programming Language :: C++
Classifier: Operating System :: OS Independent
Classifier: Topic :: Scientific/Engineering :: Bio-Informatics
Requires-Python: >=3.6
License-File: COPYING
